ducts_client/__init__.py
ducts_client/controllers.py
ducts_client/ducts.py
ducts_client/event_listeners.py
ducts_client/events.py
ducts_client-0.0.5.dist-info/LICENSE.txt
ducts_client-0.0.5.dist-info/METADATA
ducts_client-0.0.5.dist-info/WHEEL
ducts_client-0.0.5.dist-info/top_level.txt
ducts_client-0.0.5.dist-info/RECORD
